rpi_metrics/__init__.py
rpi_metrics/server/__init__.py
rpi_metrics/server/get_commit_info.sh
rpi_metrics/server/rpi-metricsd.service
rpi_metrics/server/rpi_metrics_server.py
rpi_metrics/server/static/css/styles.css
rpi_metrics/server/static/js/script.js
rpi_metrics/server/templates/index.html
rpi_metrics_server-1.0.0.dist-info/licenses/LICENSE
rpi_metrics_server-1.0.0.dist-info/METADATA
rpi_metrics_server-1.0.0.dist-info/WHEEL
rpi_metrics_server-1.0.0.dist-info/entry_points.txt
rpi_metrics_server-1.0.0.dist-info/top_level.txt
rpi_metrics_server-1.0.0.dist-info/RECORD
