Metadata-Version: 2.4
Name: rpi-metrics-server
Version: 1.0.0
Summary: Monitor and manage Raspberry Pi system metrics via a Flask server
Home-page: https://github.com/QinCai-rui/RPi-Metrics
Author: QinCai-rui
Author-email: raymontqin_rui@outlook.com
Classifier: Programming Language :: Python :: 3
Classifier: License :: OSI Approved :: GNU General Public License v3 (GPLv3)
Classifier: Operating System :: POSIX :: Linux
Classifier: Topic :: System :: Monitoring
Classifier: Framework :: Flask
Requires-Python: >=3.6
License-File: LICENSE
Requires-Dist: flask
Requires-Dist: flask-limiter
Dynamic: author
Dynamic: author-email
Dynamic: classifier
Dynamic: description
Dynamic: description-content-type
Dynamic: home-page
Dynamic: license-file
Dynamic: requires-dist
Dynamic: requires-python
Dynamic: summary
